<?xml version = '1.0' encoding = 'UTF-8'?>
<Relation class="oracle.dbtools.crest.model.design.logical.Relation" name="Relation_18" directorySegmentName="seg_0" id="20BAF931-3857-CC51-DED0-93DB020B026A">
<createdBy>Personal</createdBy>
<createdTime>2021-12-19 23:45:39 UTC</createdTime>
<ownerDesignName>proyecto</ownerDesignName>
<engineerTo>
<item key="25826295-0E8D-8F26-7470-FDC820B2AD0C" value="true"/>
</engineerTo>
<targetPk>C9907784-F1F8-41D3-1912-AA204034FFEC</targetPk>
<identifying>false</identifying>
<optionalSource>true</optionalSource>
<optionalTarget>false</optionalTarget>
<sourceCardinality>1</sourceCardinality>
<sourceEntity>574BBD97-B08B-7E3A-1C61-A81D0A07FFBA</sourceEntity>
<targetCardinalityString>*</targetCardinalityString>
<targetEntity>574BBD97-B08B-7E3A-1C61-A81D0A07FFBA</targetEntity>
<transferable>true</transferable>
</Relation>